hicue/__init__.py
hicue/displays.py
hicue/displays_opti.py
hicue/hicue.py
hicue/hicue_opti.py
hicue/imports.py
hicue/imports_opti.py
hicue/io.py
hicue/parser.py
hicue/utils.py
hicue/utils_opti.py
hicue/version.py
hicue/classes/AsyncDisplays.py
hicue/classes/MatrixExtractorLauncher.py
hicue/classes/PairFormater.py
hicue/classes/Pileup.py
hicue/classes/RandomSelector.py
hicue/classes/Reader.py
hicue/classes/__init__.py
hicue/classes/imports.py
hicue/classes/utils.py
hicue/cli/__init__.py
hicue/cli/annotate.py
hicue/cli/cli.py
hicue/cli/compare.py
hicue/cli/custom_types.py
hicue/cli/extract.py
hicue/cli/imports.py
hicue/cli/separate.py
hicue/cli/tracks.py
hicue/workers/Aggregator.py
hicue/workers/Annotator.py
hicue/workers/Extracter.py
hicue/workers/FileStreamer.py
hicue/workers/MatrixExtractor.py
hicue/workers/PairFormater.py
hicue/workers/Parser.py
hicue/workers/RandomSelector.py
hicue/workers/Separator.py
hicue/workers/SubmatrixFormater.py
hicue/workers/__init__.py
hicue/workers/imports.py
hicue/workers/utils.py
hicue-0.3.5.dist-info/METADATA
hicue-0.3.5.dist-info/WHEEL
hicue-0.3.5.dist-info/entry_points.txt
hicue-0.3.5.dist-info/licenses/LICENSE
hicue-0.3.5.dist-info/RECORD
