Metadata-Version: 2.4
Name: hicue
Version: 0.3.5
Summary: A visualisation tool for Hi-C dataset.
Project-URL: Homepage, https://github.com/Mae-4815162342/HiCue
Project-URL: Issues, https://github.com/Mae-4815162342/HiCue/issues
Author-email: Maelys Delouis <maelys.delouis@pasteur.fr>
License: CC BY-NC 4.0
License-File: LICENSE
Classifier: Development Status :: 4 - Beta
Classifier: Intended Audience :: Science/Research
Classifier: Operating System :: OS Independent
Classifier: Programming Language :: Python :: 3
Classifier: Programming Language :: Python :: 3.10
Classifier: Programming Language :: Python :: 3.11
Classifier: Programming Language :: Python :: 3.12
Classifier: Topic :: Scientific/Engineering :: Bio-Informatics
Requires-Python: >=3.10
Requires-Dist: bcbio-gff
Requires-Dist: chromosight
Requires-Dist: click
Requires-Dist: cooler>=0.10
Requires-Dist: matplotlib
Requires-Dist: numpy
Requires-Dist: pandas>=1.5.0
Requires-Dist: pybigwig
Provides-Extra: dev
Requires-Dist: black; extra == 'dev'
Requires-Dist: codecov; extra == 'dev'
Requires-Dist: hatch; extra == 'dev'
Requires-Dist: hatchling; extra == 'dev'
Requires-Dist: ipython; extra == 'dev'
Requires-Dist: mypy; extra == 'dev'
Requires-Dist: pylint; extra == 'dev'
Requires-Dist: pytest; extra == 'dev'
Requires-Dist: pytest-cov; extra == 'dev'
Requires-Dist: pytest-order; extra == 'dev'
Requires-Dist: pytest-pylint; extra == 'dev'
Requires-Dist: ruff; extra == 'dev'
Requires-Dist: twine; extra == 'dev'
Provides-Extra: test
Requires-Dist: codecov; extra == 'test'
Requires-Dist: pylint; extra == 'test'
Requires-Dist: pytest; extra == 'test'
Requires-Dist: pytest-cov; extra == 'test'
Requires-Dist: pytest-order; extra == 'test'
Requires-Dist: pytest-pylint; extra == 'test'
Requires-Dist: ruff; extra == 'test'
